[
    {
        "baslik": "UFC: F…ôrman H…ôs…ônov ABŇě-d…ôn olan r…ôqibin…ô qalib g…ôlib",
        "link": "https://apa.az/fighting-sports/ufc-ferman-hesenov-abs-den-olan-reqibine-qalib-gelib-976709",
        "resim": "https://apa.az/storage/news/2026/june/27/resize/6a3ffeb84fe416a3ffeb84fe4217825788726a3ffeb84fe3f6a3ffeb84fe40.webp",
        "kaynak": "APA",
        "zaman": "27.06.2026 | 20:42"
    },
    {
        "baslik": "Fitso: Slovakiya NATO sammitind…ô Ukraynaya yeni h…ôrbi kredit…ô d…ôst…ôk verm…ôy…ôc…ôk",
        "link": "https://apa.az/europe/fitso-slovakiya-nato-sammitinde-ukraynaya-yeni-herbi-kredite-destek-vermeyecek-976708",
        "resim": "https://apa.az/storage/news/2026/june/27/resize/6a3ff3ca12d706a3ff3ca12d7117825760746a3ff3ca12d6e6a3ff3ca12d6f.jpeg",
        "kaynak": "APA",
        "zaman": "27.06.2026 | 20:26"
    },
    {
        "baslik": "Az…ôrbaycandan tranzit ke√ßm…ôkl…ô Erm…ônistana buńüda g√∂nd…ôril…ôc…ôk",
        "link": "https://apa.az/corridors/azerbaycandan-tranzit-kecmekle-ermenistana-bugda-gonderilecek-976706",
        "resim": "https://apa.az/storage/news/2026/june/27/resize/6a3ff1d117a216a3ff1d117a22178257556999449e3945d5d36b139802aeb94d7298.jpeg",
        "kaynak": "APA",
        "zaman": "27.06.2026 | 19:51"
    },
    {
        "baslik": "Tovuzda q…ôza olub, √∂l…ôn v…ô x…ôsar…ôt alanlar var - YENńįL∆ŹNńįB",
        "link": "https://apa.az/incident/tovuzda-qeza-olub-olen-ve-xesaret-alanlar-var-yenilenib-976704",
        "resim": "https://apa.az/storage/news/2026/june/27/resize/6a3fec9da6c3e6a3fec9da6c3f17825742376a3fec9da6c3c6a3fec9da6c3d.jfif",
        "kaynak": "APA",
        "zaman": "27.06.2026 | 19:27"
    },
    {
        "baslik": "Ňě…ôkid…ô sel n…ôtic…ôsind…ô bir ne√ß…ô k…ôndin yolu bańülanńĪb - VńįDEO",
        "link": "https://apa.az/incident/sekide-sel-neticesinde-bir-nece-kendin-yolu-baglanib-video-976698",
        "resim": "https://apa.az/storage/news/2026/june/27/resize/6a3fe787261406a3fe7872614317825729358c287e1e6768cbed0e28ea6b3c3c9dce.jpeg",
        "kaynak": "APA",
        "zaman": "27.06.2026 | 19:00"
    },
    {
        "baslik": "Ceyhun Bayramovla Hakan Fidan arasńĪnda telefon danńĪŇüńĪńüńĪ olub",
        "link": "https://apa.az/domestic-policy/ceyhun-bayramovla-hakan-fidan-arasinda-telefon-danisigi-olub-976701",
        "resim": "https://apa.az/storage/news/2026/june/27/resize/6a3fe541929fc6a3fe541929fd17825723536a3fe541929fa6a3fe541929fb.png",
        "kaynak": "APA",
        "zaman": "27.06.2026 | 18:58"
    },
    {
        "baslik": "G√∂y√ßayda √ßaya yńĪxńĪlan 57 yaŇülńĪ kiŇüi xilas edilib",
        "link": "https://apa.az/incident/goycayda-caya-yixilan-57-yasli-kisi-xilas-edilib-976697",
        "resim": "https://apa.az/storage/news/2026/june/27/resize/6a3fe0912d93c6a3fe0912d93d178257115334fa7f0140d202e61ac97722bb79c652.jpg",
        "kaynak": "APA",
        "zaman": "27.06.2026 | 18:42"
    },
    {
        "baslik": "\"Heyd…ôr ∆Źliyev Kuboku\" uńürunda turnirin qalibi FHN komandasńĪ olub",
        "link": "https://apa.az/social/heyder-eliyev-kuboku-ugrunda-turnirin-qalibi-fhn-komandasi-olub-976693",
        "resim": "https://apa.az/storage/news/2026/june/27/resize/6a3fde055769a6a3fde055769b17825705016a3fde05576986a3fde0557699.jpg",
        "kaynak": "APA",
        "zaman": "27.06.2026 | 18:40"
    },
    {
        "baslik": "∆ŹfqanńĪstanda 6,2 bal g√ľc√ľnd…ô z…ôlz…ôl…ô olub",
        "link": "https://apa.az/asia/efqanistanda-62-bal-gucunde-zelzele-olub-976694",
        "resim": "https://apa.az/storage/news/2026/june/27/resize/6a3fde75632d36a3fde75632d4178257061341ec0c20cdaeec208757615635148623.jpg",
        "kaynak": "APA",
        "zaman": "27.06.2026 | 18:31"
    },
    {
        "baslik": "UFC: Braziliya t…ômsil√ßisind…ôn √ß…ôtin q…ôl…ôb…ô",
        "link": "https://apa.az/fighting-sports/ufc-braziliya-temsilcisinden-cetin-qelebe-976687",
        "resim": "https://apa.az/storage/news/2026/june/27/resize/6a3fda90a66b06a3fda90a66b117825696166a3fda90a66ae6a3fda90a66af.webp",
        "kaynak": "APA",
        "zaman": "27.06.2026 | 18:13"
    },
    {
        "baslik": "\"Xaricd…ô yaŇüamaq insana baŇüqa m…ôd…ôniyy…ôtin bir par√ßasńĪ olmańüńĪ √∂yr…ôdir\" - Surix sakini S…ôriyy…ô",
        "link": "https://www.bbc.com/azeri/articles/c0jydlnz536o?at_medium=RSS&at_campaign=rss",
        "resim": "",
        "kaynak": "BBC Az…ôrbaycanca",
        "zaman": "26.06.2026 | 10:57"
    },
    {
        "baslik": "M√ľxalif…ôt niy…ô mitinq ke√ßirmir?",
        "link": "https://www.bbc.com/azeri/articles/cnv9enj4584o?at_medium=RSS&at_campaign=rss",
        "resim": "",
        "kaynak": "BBC Az…ôrbaycanca",
        "zaman": "26.06.2026 | 10:14"
    },
    {
        "baslik": "Az…ôrbaycana qarŇüńĪ AŇěPA q…ôtnam…ôsi",
        "link": "https://www.bbc.com/azeri/articles/cgmdx2n9pj0o?at_medium=RSS&at_campaign=rss",
        "resim": "",
        "kaynak": "BBC Az…ôrbaycanca",
        "zaman": "25.06.2026 | 18:54"
    },
    {
        "baslik": "Venesuela: hava limanńĪnda z…ôlz…ôl…ô anńĪ",
        "link": "https://www.bbc.com/azeri/articles/crm0xv72d93o?at_medium=RSS&at_campaign=rss",
        "resim": "",
        "kaynak": "BBC Az…ôrbaycanca",
        "zaman": "25.06.2026 | 16:47"
    },
    {
        "baslik": "Benzinsiz yay. Yanacaq probleml…ôri onlarla Rusiya regionuna t…ôsir edib",
        "link": "https://www.bbc.com/azeri/articles/c2kyn37dj5qo?at_medium=RSS&at_campaign=rss",
        "resim": "",
        "kaynak": "BBC Az…ôrbaycanca",
        "zaman": "24.06.2026 | 15:38"
    },
    {
        "baslik": "KiŇüi musiqi√ßil…ôrl…ô baŇüńĪ a√ßńĪq konsert: 74 Ňüallaq",
        "link": "https://www.bbc.com/azeri/articles/c4gyk77ljn7o?at_medium=RSS&at_campaign=rss",
        "resim": "",
        "kaynak": "BBC Az…ôrbaycanca",
        "zaman": "23.06.2026 | 12:29"
    },
    {
        "baslik": "ArńĪqlamańüńĪn a√ßarńĪ yem…ôyinizd…ôn z√∂vq almaq ola bil…ôr",
        "link": "https://www.bbc.com/azeri/articles/cz6vw574629o?at_medium=RSS&at_campaign=rss",
        "resim": "",
        "kaynak": "BBC Az…ôrbaycanca",
        "zaman": "23.06.2026 | 08:36"
    },
    {
        "baslik": "‚ÄúBiz…ô deyirl…ôr ki, k√∂√ßm…ôs…ôn, evini darmadańüńĪn ed…ôc…ôyik‚ÄĚ",
        "link": "https://www.bbc.com/azeri/articles/cp8lz7zl24mo?at_medium=RSS&at_campaign=rss",
        "resim": "",
        "kaynak": "BBC Az…ôrbaycanca",
        "zaman": "22.06.2026 | 15:46"
    },
    {
        "baslik": "∆Źhval-ruhiyy…ôy…ô yaxŇüńĪ t…ôsir ed…ô bil…ôc…ôk qidalar",
        "link": "https://www.bbc.com/azeri/articles/c4g8nm23rzpo?at_medium=RSS&at_campaign=rss",
        "resim": "",
        "kaynak": "BBC Az…ôrbaycanca",
        "zaman": "19.06.2026 | 14:47"
    },
    {
        "baslik": "Az…ôrbaycanda √ľzr videolarńĪ niy…ô yayńĪlńĪr?",
        "link": "https://www.bbc.com/azeri/articles/c6216329ng3o?at_medium=RSS&at_campaign=rss",
        "resim": "",
        "kaynak": "BBC Az…ôrbaycanca",
        "zaman": "18.06.2026 | 12:32"
    }
]